tests/__init__.py
tests/test_elf_size.py
tests/test_exe_import_api.py
tests/test_filetype.py
tests/test_get_special_str_speed.py
tests/test_jpg_tail.py
tests/test_packer.py
tests/test_pe_cert_name.py
tests/test_pe_compile_time.py
tests/test_pe_dll_name.py
tests/test_pe_pdb.py
tests/test_pe_resource.py
tests/test_pe_size.py
tests/test_pe_versioninfo.py
tests/test_recommended_tool.py
tests/test_str.py
tests/test_windows_style_file_size.py
tests/test_yara_chinese_path.py
xanalyzer/VERSION
xanalyzer/__init__.py
xanalyzer/config.py
xanalyzer/file.py
xanalyzer/main.py
xanalyzer/url.py
xanalyzer/utils.py
xanalyzer/data/UserDB.TXT
xanalyzer/data/tools_info.json
xanalyzer/data/yara_rules/packers/UPX_PE.yar
xanalyzer/file_process/__init__.py
xanalyzer/file_process/elf.py
xanalyzer/file_process/jpg.py
xanalyzer/file_process/pe.py
xanalyzer-1.2.0.dist-info/METADATA
xanalyzer-1.2.0.dist-info/WHEEL
xanalyzer-1.2.0.dist-info/entry_points.txt
xanalyzer-1.2.0.dist-info/top_level.txt
xanalyzer-1.2.0.dist-info/RECORD
