Metadata-Version: 2.4
Name: xanalyzer
Version: 1.2.0
Summary: Analyzer for files and urls
Author: qux-bbb
Requires-Dist: python-magic-bin==0.4.14; platform_system == "Windows"
Requires-Dist: python-magic==0.4.27; platform_system == "Linux"
Requires-Dist: signify==0.5.2
Requires-Dist: pefile==2021.9.3
Requires-Dist: requests==2.32.4
Requires-Dist: coloredlogs==15.0.1
Requires-Dist: pyelftools==0.28
Requires-Dist: yara-python==4.3.1
Dynamic: author
Dynamic: description
Dynamic: description-content-type
Dynamic: requires-dist
Dynamic: summary
